ppps/__init__.py
ppps/lib/main.py
ppps/res/glob.py
ppps-0.0.10.7.dist-info/LICENSE
ppps-0.0.10.7.dist-info/METADATA
ppps-0.0.10.7.dist-info/WHEEL
ppps-0.0.10.7.dist-info/top_level.txt
ppps-0.0.10.7.dist-info/RECORD
