Metadata-Version: 2.1
Name: ppps
Version: 0.0.10.7
Summary: pre-preprocessor for C/C++
Home-page: https://github.com/tunapro1234/proprepros/
Author: TUNAPRO1234
Author-email: tunagul54@gmail.com
License: MIT
Download-URL: https://github.com/tunapro1234/proprepros/archive/v0.0.10.7-alpha.tar.gz
Project-URL: Bug Tracker, https://github.com/pypa/sampleproject/issues
Keywords: c,preprocessor,pre-preprocessor
Platform: UNKNOWN
Classifier: Intended Audience :: Developers
Classifier: Development Status :: 3 - Alpha
Classifier: Programming Language :: Python :: 3.8
Classifier: License :: OSI Approved :: MIT License
Classifier: Topic :: Software Development :: Build Tools
Requires-Python: >=3.8
